README.txt
setup.cfg
setup.py
collective/__init__.py
collective.topicitemsevent.egg-info/PKG-INFO
collective.topicitemsevent.egg-info/SOURCES.txt
collective.topicitemsevent.egg-info/dependency_links.txt
collective.topicitemsevent.egg-info/entry_points.txt
collective.topicitemsevent.egg-info/namespace_packages.txt
collective.topicitemsevent.egg-info/not-zip-safe
collective.topicitemsevent.egg-info/paster_plugins.txt
collective.topicitemsevent.egg-info/requires.txt
collective.topicitemsevent.egg-info/top_level.txt
collective/topicitemsevent/__init__.py
collective/topicitemsevent/configure.zcml
collective/topicitemsevent/event.py
collective/topicitemsevent/handlers.py
collective/topicitemsevent/tests.py
collective/topicitemsevent/browser/__init__.py
collective/topicitemsevent/browser/configure.zcml
collective/topicitemsevent/browser/interfaces.py
collective/topicitemsevent/browser/views.py
collective/topicitemsevent/profiles/default/browserlayer.xml
collective/topicitemsevent/profiles/default/metadata.xml
docs/HISTORY.txt
docs/INSTALL.txt
docs/LICENSE.GPL
docs/LICENSE.txt