Metadata-Version: 1.0
Name: collective.topicitemsevent
Version: 0.1.1
Summary: Facilitate flexible scheduled notifications in Plone: Fire 'Topic Item Events' for items in a Topic
Home-page: http://plone.org/products/collective.topicitemsevent
Author: Kees Hink
Author-email: hink@gw20e.com
License: GPL
Keywords: Plone notifications
Platform: UNKNOWN
Classifier: Framework :: Plone
Classifier: Programming Language :: Python
